odoo/addons/stock_move_line_lock_qty_done/README.rst
odoo/addons/stock_move_line_lock_qty_done/__init__.py
odoo/addons/stock_move_line_lock_qty_done/__manifest__.py
odoo/addons/stock_move_line_lock_qty_done/i18n/it.po
odoo/addons/stock_move_line_lock_qty_done/i18n/stock_move_line_lock_qty_done.pot
odoo/addons/stock_move_line_lock_qty_done/models/__init__.py
odoo/addons/stock_move_line_lock_qty_done/models/res_company.py
odoo/addons/stock_move_line_lock_qty_done/models/res_config_settings.py
odoo/addons/stock_move_line_lock_qty_done/models/stock_move_line.py
odoo/addons/stock_move_line_lock_qty_done/readme/CONFIGURE.rst
odoo/addons/stock_move_line_lock_qty_done/readme/CONTRIBUTORS.rst
odoo/addons/stock_move_line_lock_qty_done/readme/DESCRIPTION.rst
odoo/addons/stock_move_line_lock_qty_done/security/res_groups.xml
odoo/addons/stock_move_line_lock_qty_done/static/description/icon.png
odoo/addons/stock_move_line_lock_qty_done/static/description/index.html
odoo/addons/stock_move_line_lock_qty_done/tests/__init__.py
odoo/addons/stock_move_line_lock_qty_done/tests/test_stock_move_line_lock_qty_done.py
odoo/addons/stock_move_line_lock_qty_done/views/res_config_settings_views.xml
odoo_addon_stock_move_line_lock_qty_done-16.0.1.1.0.2.dist-info/METADATA
odoo_addon_stock_move_line_lock_qty_done-16.0.1.1.0.2.dist-info/WHEEL
odoo_addon_stock_move_line_lock_qty_done-16.0.1.1.0.2.dist-info/top_level.txt
odoo_addon_stock_move_line_lock_qty_done-16.0.1.1.0.2.dist-info/RECORD
